MANIFEST.in
README.md
setup.py
db3.egg-info/PKG-INFO
db3.egg-info/SOURCES.txt
db3.egg-info/dependency_links.txt
db3.egg-info/not-zip-safe
db3.egg-info/requires.txt
db3.egg-info/top_level.txt
ssdb/__init__.py
ssdb/hash.py
ssdb/kv.py
ssdb/queue.py
ssdb/todo.py
ssdb/z_hash.py